pyrkube/__init__.py
pyrkube/adict.py
pyrkube/client.py
pyrkube/config.py
pyrkube/exceptions.py
pyrkube/hosts.py
pyrkube/objects.py
pyrkube/util.py
pyrkube-0.2.5.dist-info/DESCRIPTION.rst
pyrkube-0.2.5.dist-info/METADATA
pyrkube-0.2.5.dist-info/RECORD
pyrkube-0.2.5.dist-info/WHEEL
pyrkube-0.2.5.dist-info/metadata.json
pyrkube-0.2.5.dist-info/top_level.txt
tasks/__init__.py
tasks/docker.py
tasks/py.py
tasks/test.py
test/__init__.py
test/test_client.py
test/test_hosts.py
test/test_objects.py
