Metadata-Version: 2.0
Name: pyrkube
Version: 0.2.5
Summary: Readonly wrapper for pykube with a different focus
Home-page: https://github.com/telephoneorg/pyrkube
Author: Joe Black
Author-email: me@joeblack.nyc
License: Apache 2.0
Download-URL: https://github.com/telephoneorg/pyrkube/tarball/0.2.5
Keywords: kubernetes,clustering,templating
Platform: UNKNOWN
Classifier: Development Status :: 3 - Alpha
Classifier: Intended Audience :: Developers
Classifier: Operating System :: OS Independent
Classifier: Natural Language :: English
Classifier: License :: OSI Approved :: Apache Software License
Classifier: Programming Language :: Python :: 3 :: Only
Classifier: Topic :: Internet :: WWW/HTTP
Classifier: Topic :: System :: Clustering
Requires-Dist: pykube
Requires-Dist: six
